latency_monitor/__init__.py
latency_monitor/api.py
latency_monitor/core.py
latency_monitor/defaults.py
latency_monitor/main.py
latency_monitor/metrics/__init__.py
latency_monitor/metrics/accumulator.py
latency_monitor/metrics/cli.py
latency_monitor/metrics/clickhouse.py
latency_monitor/metrics/datadog.py
latency_monitor/metrics/log.py
latency_monitor/metrics/pushgateway.py
latency_monitor/metrics/zeromq.py
latency_monitor-0.1.0.dist-info/licenses/LICENSE
latency_monitor-0.1.0.dist-info/METADATA
latency_monitor-0.1.0.dist-info/WHEEL
latency_monitor-0.1.0.dist-info/entry_points.txt
latency_monitor-0.1.0.dist-info/top_level.txt
latency_monitor-0.1.0.dist-info/RECORD
