Metadata-Version: 2.4
Name: latency-monitor
Version: 0.1.0
Summary: Daemon that acts as both client & server for monitoring latency between different endpoints
Author-email: Mircea Ulinic <ping@mirceaulinic.net>
Maintainer-email: Mircea Ulinic <ping@mirceaulinic.net>
License-Expression: Apache-2.0
Project-URL: Homepage, https://github.com/mirceaulinic/latency-monitor
Project-URL: Documentation, https://github.com/mirceaulinic/latency-monitor/README.md
Project-URL: Repository, https://github.com/mirceaulinic/latency-monitor.git
Project-URL: Issues, https://github.com/mirceaulinic/latency-monitor/issues
Keywords: tcp,udp,latency,datadog,prometheus
Classifier: Topic :: Utilities
Classifier: Topic :: System :: Monitoring
Classifier: Topic :: System :: Networking
Classifier: Topic :: System :: Networking :: Monitoring
Classifier: Development Status :: 4 - Beta
Classifier: Intended Audience :: Developers
Classifier: Intended Audience :: Science/Research
Classifier: Intended Audience :: System Administrators
Classifier: Intended Audience :: Telecommunications Industry
Classifier: Programming Language :: Python :: 3
Classifier: Programming Language :: Python :: 3.11
Classifier: Programming Language :: Python :: 3.12
Classifier: Programming Language :: Python :: 3.13
Classifier: Operating System :: OS Independent
Requires-Python: >=3.11
License-File: LICENSE
Provides-Extra: datadog
Requires-Dist: datadog-api-client>=2.47.0; extra == "datadog"
Provides-Extra: prometheus
Requires-Dist: prometheus-client>=0.23.1; extra == "prometheus"
Provides-Extra: zeromq
Requires-Dist: pyzmq>=27.1.0; extra == "zeromq"
Provides-Extra: clickhouse
Requires-Dist: clickhouse-connect>=0.10.0; extra == "clickhouse"
Dynamic: license-file
